{
    "feed": [
        {
            "id": "feed_001",
            "type": "company",
            "author": {
                "authorId": "comp_001",
                "name": "Podium",
                "imageUrl": "https://upload.wikimedia.org/wikipedia/commons/6/61/Podium_Logo_Official.png"
            },
            "postSubtitle": "Product Manager",
            "videoUrl": "https://stream.livestreamfails.com/video/5c67b710462a2.mp4",
            "note": "We are looking for a self starter who can get any job done that we need in any type of coding environment. Microsoft is in need of great developers that can handle many of the different projects we have."
        },
        {
            "id": "feed_002",
            "type": "company",
            "author": {
                "authorId": "comp_002",
                "name": "Apple",
                "imageUrl": "https://media.idownloadblog.com/wp-content/uploads/2018/07/Apple-logo-black-and-white.png"
            },
            "postSubtitle": "Product Manager Entry",
            "videoUrl": "https://stream.livestreamfails.com/video/5c6797ab1a640.mp4",
            "note": "We are looking for a self starter who can get any job done that we need in any type of coding environment. Microsoft is in need of great developers that can handle many of the different projects we have…"
        },
        {
            "id": "feed_003",
            "type": "company",
            "author": {
                "authorId": "comp_003",
                "name": "Google",
                "imageUrl": "https://us.123rf.com/450wm/kornienko/kornienko1611/kornienko161100200/66047248-chisinau-moldova-november-16-2016-google-logo-on-pc-screen-google-it-is-the-largest-internet-search-.jpg?ver=6"
            },
            "postSubtitle": "Senior Product Manager",
            "videoUrl": "https://stream.livestreamfails.com/video/5c66f3d85b5bb.mp4",
            "note": "We are looking for a self starter who can get any job done that we need in any type of coding environment. Microsoft is in need of great developers that can handle many of the different projects we have…"
        },
        {
            "id": "feed_004",
            "type": "company",
            "author": {
                "authorId": "comp_004",
                "name": "Facebook",
                "imageUrl": "https://cdn3.iconfinder.com/data/icons/glypho-social-and-other-logos/64/logo-facebook-512.png"
            },
            "postSubtitle": "Product Manager",
            "videoUrl": "https://stream.livestreamfails.com/video/5c667ae367b58.mp4",
            "note": "We are looking for a self starter who can get any job done that we need in any type of coding environment. Microsoft is in need of great developers that can handle many of the different projects we have…"
        },
        {
            "id": "feed_005",
            "type": "company",
            "author": {
                "authorId": "comp_005",
                "name": "Instagram",
                "imageUrl": "https://www.wpvm.org/wp-content/uploads/2020/04/instagram-1581266_640.jpg"
            },
            "postSubtitle": "PM",
            "videoUrl": "https://stream.livestreamfails.com/video/5baed037dee0f.mp4",
            "note": "We are looking for a self starter who can get any job done that we need in any type of coding environment. Microsoft is in need of great developers that can handle many of the different projects we have…"
        },
        {
            "id": "feed_006",
            "type": "company",
            "author": {
                "authorId": "comp_006",
                "name": "SimpleNexus",
                "imageUrl": "https://pbs.twimg.com/profile_images/1273021459036692480/4jZo77Nw_400x400.jpg"
            },
            "postSubtitle": "Product Manager",
            "videoUrl": "https://stream.livestreamfails.com/video/5bde5a2496a8f.mp4",
            "note": "We are looking for a self starter who can get any job done that we need in any type of coding environment. Microsoft is in need of great developers that can handle many of the different projects we have…"
        },
        {
            "id": "feed_007",
            "type": "company",
            "author": {
                "authorId": "comp_007",
                "name": "Weave",
                "imageUrl": "https://"
            },
            "postSubtitle": "Product Manager",
            "videoUrl": "https://stream.livestreamfails.com/video/5bdaaec4e4acf.mp4",
            "note": "We are looking for a self starter who can get any job done that we need in any type of coding environment. Microsoft is in need of great developers that can handle many of the different projects we have…"
        },
        {
            "id": "feed_008",
            "type": "company",
            "author": {
                "authorId": "comp_008",
                "name": "WorkFront",
                "imageUrl": "https://res-2.cloudinary.com/crunchbase-production/image/upload/c_lpad,h_256,w_256,f_auto,q_auto:eco/xofgjos2nwfbahipkshf"
            },
            "postSubtitle": "Product Manager",
            "videoUrl": "https://stream.livestreamfails.com/video/5b0708e575662.mp4",
            "note": "We are looking for a self starter who can get any job done that we need in any type of coding environment. Microsoft is in need of great developers that can handle many of the different projects we have…"
        },
        {
            "id": "feed_009",
            "type": "company",
            "author": {
                "authorId": "comp_009",
                "name": "Netflix",
                "imageUrl": "https://logodix.com/logo/69184.jpg"
            },
            "postSubtitle": "Product Manager",
            "videoUrl": "https://stream.livestreamfails.com/video/5b4fc189ac34a.mp4",
            "note": "We are looking for a self starter who can get any job done that we need in any type of coding environment. Microsoft is in need of great developers that can handle many of the different projects we have…"
        },
        {
            "id": "feed_0010",
            "type": "company",
            "author": {
                "authorId": "comp_0010",
                "name": "LinkedIn",
                "imageUrl": "https://cdn4.iconfinder.com/data/icons/social-messaging-ui-color-shapes-2-free/128/social-linkedin-circle-512.png"
            },
            "postSubtitle": "Product Manager",
            "videoUrl": "https://stream.livestreamfails.com/video/5b9d5cd0f121e.mp4",
            "note": "We are looking for a self starter who can get any job done that we need in any type of coding environment. Microsoft is in need of great developers that can handle many of the different projects we have…"
        }
    ]
}
